pipe_viper/main.py
pipe_viper-0.1.2.dist-info/WHEEL
pipe_viper-0.1.2.dist-info/METADATA
pipe_viper-0.1.2.dist-info/RECORD
