Metadata-Version: 2.1
Name: pipe-viper
Version: 0.1.2
Summary: Pwsh utils for python
Home-page: https://github.com/Phelsong/pipe_viper
License: MIT
Author: Josh S Wilkinson
Author-email: JoshsWilkinson@Outlook.com
Requires-Python: >=3.8,<4.0
Classifier: License :: OSI Approved :: MIT License
Classifier: Programming Language :: Python :: 3
Classifier: Programming Language :: Python :: 3.8
Classifier: Programming Language :: Python :: 3.9
Classifier: Programming Language :: Python :: 3.10
Classifier: Programming Language :: Python :: 3.11
Project-URL: Repository, https://github.com/Phelsong/pipe_viper
